nwsubprocess/__init__.py
nwsubprocess/__main__.py
nwsubprocess/execution.py
nwsubprocess/process.py
nwsubprocess/utils.py
nwsubprocess-0.2.2.dist-info/WHEEL
nwsubprocess-0.2.2.dist-info/METADATA
nwsubprocess-0.2.2.dist-info/RECORD
